{"cameraMode":{"drawMode":0,"name":"Shaded","section":"Shading Mode"},"sceneLighting":true,"audioPlay":false,"sceneViewState":{"m_AlwaysRefresh":false,"showFog":true,"showSkybox":true,"showFlares":true,"showImageEffects":true,"showParticleSystems":true,"showVisualEffectGraphs":true,"m_FxEnabled":true},"in2DMode":false,"pivot":{"x":-20.181621551513673,"y":-7.513297080993652,"z":-5.372511863708496},"rotation":{"x":0.16458015143871308,"y":-0.7274879813194275,"z":0.18730883300304414,"w":0.6392130851745606},"size":15.398638725280762,"orthographic":false}